MANIFEST.in
README.md
setup.py
RoyGBiv.egg-info/PKG-INFO
RoyGBiv.egg-info/SOURCES.txt
RoyGBiv.egg-info/dependency_links.txt
RoyGBiv.egg-info/requires.txt
RoyGBiv.egg-info/top_level.txt
roygbiv/Counter.py
roygbiv/__init__.py
roygbiv/test.py