Metadata-Version: 1.0
Name: RoyGBiv
Version: 0.3.1
Summary: A set of image color analysis tools
Home-page: https://github.com/givp/RoyGBiv
Author: Giv Parvaneh
Author-email: UNKNOWN
License: http://www.opensource.org/licenses/mit-license.php
Platform: UNKNOWN
Classifier: Programming Language :: Python
